{
  "data": {
    "article": {},
    "attachments": {},
    "author_id": "1522094771136831488",
    "conversation_id": "2028861746761629992",
    "created_at": "2026-03-03T15:55:09.000Z",
    "edit_controls": {
      "editable_until": "2026-03-03T16:55:09.000Z",
      "edits_remaining": 5,
      "is_edit_eligible": true
    },
    "edit_history_tweet_ids": [
      "2028861746761629992"
    ],
    "entities": {
      "urls": [
        {
          "display_url": "x.com/jingzhny11/sta…",
          "end": 31,
          "expanded_url": "https://twitter.com/jingzhny11/status/2028205121348555232",
          "start": 8,
          "url": "https://t.co/GI9Ly6GVM5"
        }
      ]
    },
    "geo": {},
    "id": "2028861746761629992",
    "lang": "zh",
    "note_tweet": {
      "entities": {}
    },
    "possibly_sensitive": false,
    "public_metrics": {
      "bookmark_count": 0,
      "impression_count": 0,
      "like_count": 0,
      "quote_count": 0,
      "reply_count": 0,
      "retweet_count": 0
    },
    "referenced_tweets": [
      {
        "id": "2028205121348555232",
        "type": "quoted"
      }
    ],
    "reply_settings": "everyone",
    "text": "這也是我支持的 https://t.co/GI9Ly6GVM5"
  },
  "includes": {
    "tweets": [
      {
        "article": {},
        "attachments": {},
        "author_id": "1522094771136831488",
        "conversation_id": "2028861746761629992",
        "created_at": "2026-03-03T15:55:09.000Z",
        "edit_controls": {
          "editable_until": "2026-03-03T16:55:09.000Z",
          "edits_remaining": 5,
          "is_edit_eligible": true
        },
        "edit_history_tweet_ids": [
          "2028861746761629992"
        ],
        "entities": {
          "urls": [
            {
              "display_url": "x.com/jingzhny11/sta…",
              "end": 31,
              "expanded_url": "https://twitter.com/jingzhny11/status/2028205121348555232",
              "start": 8,
              "url": "https://t.co/GI9Ly6GVM5"
            }
          ]
        },
        "geo": {},
        "id": "2028861746761629992",
        "lang": "zh",
        "note_tweet": {
          "entities": {}
        },
        "possibly_sensitive": false,
        "public_metrics": {
          "bookmark_count": 0,
          "impression_count": 0,
          "like_count": 0,
          "quote_count": 0,
          "reply_count": 0,
          "retweet_count": 0
        },
        "referenced_tweets": [
          {
            "id": "2028205121348555232",
            "type": "quoted"
          }
        ],
        "reply_settings": "everyone",
        "text": "這也是我支持的 https://t.co/GI9Ly6GVM5"
      },
      {
        "article": {},
        "attachments": {},
        "author_id": "1597468568290873344",
        "conversation_id": "2028164459639038458",
        "created_at": "2026-03-01T20:25:57.000Z",
        "edit_controls": {
          "editable_until": "2026-03-01T21:25:57.000Z",
          "edits_remaining": 5,
          "is_edit_eligible": false
        },
        "edit_history_tweet_ids": [
          "2028205121348555232"
        ],
        "entities": {
          "mentions": [
            {
              "end": 12,
              "id": "1736265610911428608",
              "start": 0,
              "username": "noname2095_"
            }
          ]
        },
        "geo": {},
        "id": "2028205121348555232",
        "in_reply_to_user_id": "1736265610911428608",
        "lang": "zh",
        "note_tweet": {
          "entities": {}
        },
        "possibly_sensitive": false,
        "public_metrics": {
          "bookmark_count": 0,
          "impression_count": 1599,
          "like_count": 15,
          "quote_count": 1,
          "reply_count": 0,
          "retweet_count": 0
        },
        "referenced_tweets": [
          {
            "id": "2028164459639038458",
            "type": "replied_to"
          }
        ],
        "reply_settings": "everyone",
        "text": "@noname2095_ 我一直支持药物自由啊，不止是精神药物（"
      }
    ],
    "users": [
      {
        "created_at": "2022-05-05T06:04:16.000Z",
        "description": "借来的翅膀，能划过雨幕笼罩的天空吗",
        "id": "1522094771136831488",
        "location": "Rubicon 3",
        "name": "The Raven in the Rain🏳️‍🌈",
        "pinned_tweet_id": "1906626606074052692",
        "profile_image_url": "https://pbs.twimg.com/profile_images/2007370883875381248/w_VYzmIG_normal.jpg",
        "protected": false,
        "public_metrics": {
          "followers_count": 267,
          "following_count": 1565,
          "like_count": 13570,
          "listed_count": 1,
          "media_count": 183,
          "tweet_count": 6250
        },
        "username": "Raincandy_1937",
        "verified": false
      },
      {
        "created_at": "2022-11-29T05:53:13.000Z",
        "description": "99年 \n🍥​2023/05/07 srs2025/07/31 一米九超大只\n左下的，混乱善良的，激跨的，支持精神活性物质的，ODer但水平很差的，想当黄推的，下海预备的\n感性条拉满的理想主义者ENFP\n希望一个没人再感到痛苦的世界/如果可以我希望爱、原谅与理解而不是恶、仇恨与歧视",
        "id": "1597468568290873344",
        "location": "谁人的繁星之梦",
        "name": "愿望天使DesireAngel",
        "profile_image_url": "https://pbs.twimg.com/profile_images/2024462875855900673/BMWGdQhI_normal.jpg",
        "protected": false,
        "public_metrics": {
          "followers_count": 4979,
          "following_count": 2032,
          "like_count": 115061,
          "listed_count": 21,
          "media_count": 243,
          "tweet_count": 16599
        },
        "username": "jingzhny11",
        "verified": false
      }
    ]
  }
}